numcodecs_wasm_reinterpret/__init__.py
numcodecs_wasm_reinterpret/__init__.pyi
numcodecs_wasm_reinterpret/codec.wasm
numcodecs_wasm_reinterpret/py.typed
numcodecs_wasm_reinterpret-0.4.0.dist-info/METADATA
numcodecs_wasm_reinterpret-0.4.0.dist-info/WHEEL
numcodecs_wasm_reinterpret-0.4.0.dist-info/entry_points.txt
numcodecs_wasm_reinterpret-0.4.0.dist-info/top_level.txt
numcodecs_wasm_reinterpret-0.4.0.dist-info/RECORD
